pytchuka/__init__.py
pytchuka/pytchuka.py
pytchuka-0.0.8.dist-info/LICENSE
pytchuka-0.0.8.dist-info/METADATA
pytchuka-0.0.8.dist-info/WHEEL
pytchuka-0.0.8.dist-info/entry_points.txt
pytchuka-0.0.8.dist-info/top_level.txt
pytchuka-0.0.8.dist-info/RECORD
